LICENSE
MANIFEST.in
README.rst
setup.py
wsgi_cors_middleware.py
wsgi_cors_middleware.egg-info/PKG-INFO
wsgi_cors_middleware.egg-info/SOURCES.txt
wsgi_cors_middleware.egg-info/dependency_links.txt
wsgi_cors_middleware.egg-info/top_level.txt