Metadata-Version: 1.1
Name: wsgi-cors-middleware
Version: 0.0.2
Summary: Cross Origin Resource Sharing (CORS) Middleware for WSGI Applications.
Home-page: https://github.com/moritzmhmk/wsgi-cors-middleware
Author: Moritz K.
Author-email: moritzmhmk@googlemail.com
License: MIT
Download-URL: https://github.com/moritzmhmk/wsgi-cors-middleware/archive/v0.0.2.tar.gz
Keywords: wsgi,cors,middleware
Platform: UNKNOWN
